chenpy/__init__.py
chenpy/cli.py
chenpy/client.py
chenpy/config.py
chenpy/detectors/__init__.py
chenpy/detectors/c.py
chenpy/detectors/common.py
chenpy/detectors/java.py
chenpy/detectors/js.py
chenpy/detectors/python.py
chenpy/graph.py
chenpy/logger.py
chenpy/source/__init__.py
chenpy/source/ghsa.py
chenpy/utils.py
chenpy/workspace.py
appthreat_chen-2.5.17.dist-info/METADATA
appthreat_chen-2.5.17.dist-info/WHEEL
appthreat_chen-2.5.17.dist-info/entry_points.txt
appthreat_chen-2.5.17.dist-info/licenses/LICENSE
appthreat_chen-2.5.17.dist-info/RECORD
