Metadata-Version: 2.4
Name: appthreat-chen
Version: 2.5.17
Summary: Code Hierarchy Exploration Net (chen)
License: Apache-2.0
License-File: LICENSE
Keywords: chen,code-analysis,static-analysis
Author: Team AppThreat
Author-email: cloud@appthreat.com
Requires-Python: >=3.10,<3.14
Classifier: Development Status :: 5 - Production/Stable
Classifier: Intended Audience :: Developers
Classifier: Intended Audience :: System Administrators
Classifier: License :: OSI Approved :: Apache Software License
Classifier: Operating System :: OS Independent
Classifier: Programming Language :: Python :: 3
Classifier: Programming Language :: Python :: 3.10
Classifier: Programming Language :: Python :: 3.11
Classifier: Programming Language :: Python :: 3.12
Classifier: Programming Language :: Python :: 3.13
Classifier: Topic :: Security
Classifier: Topic :: Utilities
Provides-Extra: database
Provides-Extra: science
Requires-Dist: appdirs (>=1.4.4,<2.0.0)
Requires-Dist: gitpython (>=3.1.44,<4.0.0)
Requires-Dist: httpx (>=0.27.2,<0.28.0)
Requires-Dist: oras (==0.1.26)
Requires-Dist: orjson (>=3.10.13,<4.0.0)
Requires-Dist: packageurl-python (>=0.11.2,<0.12.0)
Requires-Dist: psutil (>=6.1.1,<7.0.0)
Requires-Dist: rich (>=13.9.4,<14.0.0)
Requires-Dist: uvloop (>=0.21.0,<0.22.0) ; (sys_platform == "linux" or sys_platform == "darwin") and (extra == "science")
Requires-Dist: websockets (>=14.1,<15.0)
Project-URL: CI, https://github.com/AppThreat/chen/actions
Project-URL: Homepage, https://github.com/AppThreat/chen
Project-URL: Repository, https://github.com/AppThreat/chen
